vegabase/__init__.py
vegabase/cli.py
vegabase/config.py
vegabase/db/README.md
vegabase/db/__init__.py
vegabase/db/async_database.py
vegabase/db/database.py
vegabase/db/errors.py
vegabase/db/hooks.py
vegabase/db/py.typed
vegabase/db/schema.py
vegabase/db/types.py
vegabase/default_settings.yaml
vegabase/manifest.py
vegabase/middleware.py
vegabase/renderer.py
vegabase/ts/src/cli.ts
vegabase/ts/src/log.ts
vegabase/ts/templates/client.template.tsx
vegabase/ts/templates/route.template.tsx
vegabase/ts/templates/routeTree.template.tsx
vegabase/ts/templates/ssr-server.template.tsx
vegabase/ts/templates/ssr.template.tsx
vegabase-0.2.1.dist-info/WHEEL
vegabase-0.2.1.dist-info/entry_points.txt
vegabase-0.2.1.dist-info/METADATA
vegabase-0.2.1.dist-info/RECORD
