Metadata-Version: 2.4
Name: vegabase
Version: 0.2.1
Summary: Full-stack React + Python with zero configuration. Build modern React apps with FastAPI, Bun, Tanstack Router, and Tailwind CSS.
Keywords: react,fastapi,bun,tanstack,tailwind,ssr,full-stack
License-Expression: MIT
Classifier: Development Status :: 4 - Beta
Classifier: Framework :: FastAPI
Classifier: Intended Audience :: Developers
Classifier: License :: OSI Approved :: MIT License
Classifier: Programming Language :: Python :: 3.11
Classifier: Programming Language :: Python :: 3.12
Classifier: Topic :: Internet :: WWW/HTTP :: HTTP Servers
Requires-Dist: fastapi>=0.115.8
Requires-Dist: httpx>=0.27.0
Requires-Dist: itsdangerous>=2.0.0
Requires-Dist: python-multipart>=0.0.9
Requires-Dist: sqlalchemy>=2.0.0
Requires-Dist: pydantic>=2.0.0
Requires-Dist: dynaconf>=3.2.0
Requires-Dist: uvicorn>=0.30.0
Requires-Dist: aiosqlite>=0.20.0 ; extra == 'async'
Requires-Dist: asyncpg>=0.29.0 ; extra == 'async'
Requires-Dist: greenlet>=3.0.0 ; extra == 'async'
Requires-Dist: ruff>=0.8.0 ; extra == 'dev'
Requires-Dist: ty>=0.0.1a6 ; extra == 'dev'
Requires-Dist: psycopg[binary]>=3.0.0 ; extra == 'postgres'
Requires-Dist: pytest>=8.0.0 ; extra == 'test'
Requires-Dist: pytest-asyncio>=0.24.0 ; extra == 'test'
Requires-Dist: aiosqlite>=0.20.0 ; extra == 'test'
Requires-Dist: greenlet>=3.0.0 ; extra == 'test'
Requires-Python: >=3.11
Project-URL: Homepage, https://github.com/kjrjay/vegabase
Project-URL: Repository, https://github.com/kjrjay/vegabase
Provides-Extra: async
Provides-Extra: dev
Provides-Extra: postgres
Provides-Extra: test
